{
    "业务简述：": "自助设备百度缴费业务是指客户在百度公司一次申请银行缴费功能，后续可凭百度客户标识号和百度验证码到我行自助设备办理百度缴费业务。",
    "适用对象：": "凡在百度公司已开通银行缴费功能，且获取标识号和验证码的客户，均可持我行借记卡在我行自助终端和自动柜员机办理百度缴费业务。",
    "开办条件：": "1、客户已在百度公司开通银行缴费功能，且获取标识号和验证码；2、客户持有我行借记卡。",
    "开通流程：": "客户办理本业务前，需首先在百度公司开通银行缴费功能，且获取标识号和验证码。",
    "服务渠道与时间：": "客户可在我行自助机具（存取款一体机、ATM、查询缴费机、转账汇款机）办理该业务，业务受理时间为每日1:00-20:00。",
    "操作指南：": "1、客户插卡并输入卡片密码；在机具缴费业务模块选择“百度缴费”；2、输入“百度客户标识号”及“百度验证码”；3、系统回显客户的百度账户信息，客户确认信息正确；4、输入缴费金额并确认；5、系统回显交易成功。",
    "常见问题：": "您在我行自助机具办理百度缴费业务后如需发票，可向百度时代网络技术（北京）有限公司索取。责任声明：本页面内容仅供参考，具体业务办理标准以中国工商银行当地分行规定为准。",
    "taglist": [
        "北京分行",
        "特色业务",
        "代理缴费业务",
        "百度缴费"
    ]
}