{
    "业务简述：": "薪金卡是我行面向代发工资客户发行的主题借记卡，在借记卡金融功能基础上，通过结算套餐、费率优惠、专属协议等为我行代发工资客户提供一系列便捷、安全的金融增值服务。",
    "适用对象：": "在工行代发工资的个人客户。",
    "特色优势：": "1、结算套餐：薪金卡客户每年可享受总计36笔免手续费的结算套餐服务，业务包含异地存款、异地取款、异地汇款、跨行取款、跨行汇款。客户在1年内办理的超过套餐笔数的结算业务，按照工行对外公示的中间业务收费标准收费。2、费率优惠：薪金卡作为代发工资入账账户，免收新发卡工本费、卡片年费、小额账户管理费以及工银信使余额变动提醒费用。3、专属协议：薪金卡签订“薪金溢1号”协议后，可提高卡内活期资金收益，满足应急资金的流动性和收益性需求。",
    "申请条件：": "1、个人客户可持本人有效身份证件和原代发工资的借记卡或存折到北京地区任意工行网点申请薪金卡。原工资账户近两个月至少有1次代发工资入账明细。2、企业客户与工行开展代发工资业务合作后，可为员工批量申请开立薪金卡。",
    "服务渠道：": "1、薪金卡新办、补换卡、卡片启用等业务需在我行网点柜面办理。2、薪金卡各项金融功能同工行借记卡，支持网上银行、手机银行、ATM机、存取款一体机、自助终端使用。",
    "温馨提示：": "使用薪金卡办理非结算套餐内的其他业务时，须交纳的费用按照工行公示的中间业务收费标准执行。责任声明：本页面内容仅供参考，具体业务办理标准以中国工商银行北京市分行规定为准。",
    "taglist": [
        "北京分行",
        "特色业务",
        "特色借记卡业务",
        "工银借记卡",
        "薪金卡"
    ]
}